oneclick_client
