Metadata-Version: 2.1
Name: oneclick-client
Version: 1.0.1
Summary: Simple library to use Spectrum OneClick API.
Home-page: https://github.com/sprootik/oneclick_client.git
Author: sprootik
Author-email: sprootik89@gmail.com
License: UNKNOWN
Platform: UNKNOWN
Classifier: Development Status :: 5 - Production/Stable
Classifier: Programming Language :: Python :: 3
Classifier: Programming Language :: Python :: 3.9
Classifier: Programming Language :: Python :: 3.10
Classifier: License :: OSI Approved :: MIT License
Classifier: Operating System :: OS Independent
Requires-Python: >=3.9
